zy_test/__init__.py
zy_test/tools/__init__.py
zy_test/tools/get_resume_parse.py
zy_test-0.0.7.dist-info/METADATA
zy_test-0.0.7.dist-info/WHEEL
zy_test-0.0.7.dist-info/top_level.txt
zy_test-0.0.7.dist-info/RECORD
