Metadata-Version: 2.4
Name: zy-test
Version: 0.0.7
Summary: zy-test
Home-page: https://github.com/123123123123/zy-test
Author: admin
Author-email: admin@qq.com  
Dynamic: author
Dynamic: author-email
Dynamic: home-page
Dynamic: summary
